EVT_fitting.py
Openmax.py
compute_openmax.py
openmax_utils.py
keras_openmax/EVT_fitting.py
keras_openmax/Openmax.py
keras_openmax/__init__.py
keras_openmax/compute_openmax.py
keras_openmax/openmax_utils.py
keras_openmax_pkg/EVT_fitting.py
keras_openmax_pkg/Openmax.py
keras_openmax_pkg/__init__.py
keras_openmax_pkg/compute_openmax.py
keras_openmax_pkg/openmax_utils.py
keras_openmax-1.0.3.dist-info/LICENSE
keras_openmax-1.0.3.dist-info/METADATA
keras_openmax-1.0.3.dist-info/WHEEL
keras_openmax-1.0.3.dist-info/top_level.txt
keras_openmax-1.0.3.dist-info/RECORD
