Metadata-Version: 2.1
Name: keras-openmax
Version: 1.0.3
Summary: Keras implementation of Openmax
Home-page: https://github.com/DietmarKracht/Keras-Openmax
Author: Clemens Brackmann
Author-email: clemens.brackmann@web.de
License: UNKNOWN
Platform: UNKNOWN
Classifier: Programming Language :: Python :: 3
Classifier: License :: OSI Approved :: MIT License
Classifier: Operating System :: OS Independent
Requires-Python: >=3.6
Requires-Dist: Cython (>=0.29.15)
Requires-Dist: Keras (==2.3.1)
Requires-Dist: libmr (>=0.1.9)
Requires-Dist: matplotlib (>=3.2.0)
Requires-Dist: numpy (>=1.18.1)
Requires-Dist: Pillow (>=7.0.0)
Requires-Dist: scipy (==1.4.1)
Requires-Dist: tensorflow (==2.1.0)
Requires-Dist: tqdm (>=4.43.0)
